data_explorer/__init__.py
data_explorer/essai.py
data_explorer/getter.py
worldbank_sn_jn-0.1.0.dist-info/METADATA
worldbank_sn_jn-0.1.0.dist-info/WHEEL
worldbank_sn_jn-0.1.0.dist-info/top_level.txt
worldbank_sn_jn-0.1.0.dist-info/RECORD
